{
  "lists": [
    {
      "id": 1,
      "searchName": "png to svg"
    },
    {
      "id": 2,
      "searchName": "jpg to svg"
    },
    {
      "id": 3,
      "searchName": "svg converter"
    },
    {
      "id": 4,
      "searchName": "svg to jpg"
    },
    {
      "id": 5,
      "searchName": "svg to png"
    },
    {
      "id": 6,
      "searchName": "svg to ico"
    },
    {
      "id": 7,
      "searchName": "swf to mp4"
    },
    {
      "id": 8,
      "searchName": "webp to svg"
    },
    {
      "id": 9,
      "searchName": "pdt to philippine standard time"
    },
    {
      "id": 10,
      "searchName": "kst to cuba standard time"
    },
    {
      "id": 11,
      "searchName": "sst to est"
    },
    {
      "id": 12,
      "searchName": "aedt to sst"
    },
    {
      "id": 13,
      "searchName": "test to sst"
    },
    {
      "id": 14,
      "searchName": "avi to mp4"
    },
    {
      "id": 15,
      "searchName": "audio converter"
    },
    {
      "id": 16,
      "searchName": "avif to jpg"
    },
    {
      "id": 17,
      "searchName": "bst to pst"
    },
    {
      "id": 18,
      "searchName": "bst to est"
    },
    {
      "id": 19,
      "searchName": "png to bmp"
    },
    {
      "id": 20,
      "searchName": "video compressor"
    },
    {
      "id": 21,
      "searchName": "mp4 converter"
    },
    {
      "id": 22,
      "searchName": "cst to est"
    },
    {
      "id": 23,
      "searchName": "dds to png"
    },
    {
      "id": 24,
      "searchName": "dng to jpg"
    },
    {
      "id": 25,
      "searchName": "doc to word"
    }
  ]
}
